mozilla_nimbus_schemas/__init__.py
mozilla_nimbus_schemas/experimenter_apis/common.py
mozilla_nimbus_schemas/experimenter_apis/experiments/__init__.py
mozilla_nimbus_schemas/experimenter_apis/experiments/experiments.py
mozilla_nimbus_schemas/experimenter_apis/experiments/feature_manifests.py
mozilla_nimbus_schemas/experimenter_apis/experiments_v7/__init__.py
mozilla_nimbus_schemas/experimenter_apis/experiments_v7/experiments_v7.py
mozilla_nimbus_schemas/jetstream/__init__.py
mozilla_nimbus_schemas/jetstream/analysis_errors.py
mozilla_nimbus_schemas/jetstream/metadata.py
mozilla_nimbus_schemas/jetstream/misc.py
mozilla_nimbus_schemas/jetstream/population_sizing.py
mozilla_nimbus_schemas/jetstream/statistics.py
mozilla_nimbus_schemas/schemas/DesktopAllVersionsNimbusExperiment.schema.json
mozilla_nimbus_schemas/schemas/DesktopFeature.schema.json
mozilla_nimbus_schemas/schemas/DesktopFeatureManifest.schema.json
mozilla_nimbus_schemas/schemas/DesktopNimbusExperiment.schema.json
mozilla_nimbus_schemas/schemas/ExperimentBucketConfig.schema.json
mozilla_nimbus_schemas/schemas/ExperimentFeatureConfig.schema.json
mozilla_nimbus_schemas/schemas/ExperimentLocalizations.schema.json
mozilla_nimbus_schemas/schemas/ExperimentOutcome.schema.json
mozilla_nimbus_schemas/schemas/NimbusExperimentV7.schema.json
mozilla_nimbus_schemas/schemas/SdkFeatureManifest.schema.json
mozilla_nimbus_schemas/schemas/SdkNimbusExperiment.schema.json
mozilla_nimbus_schemas/tests/experiments/__init__.py
mozilla_nimbus_schemas/tests/experiments/fixtures/experiments/desktop/desktop-107-featureValidationOptOut.json
mozilla_nimbus_schemas/tests/experiments/fixtures/experiments/desktop/desktop-113-localizations.json
mozilla_nimbus_schemas/tests/experiments/fixtures/experiments/desktop/desktop-115-locales.json
mozilla_nimbus_schemas/tests/experiments/fixtures/experiments/desktop/desktop-123-publishedDate.json
mozilla_nimbus_schemas-3001.0.0.dist-info/LICENSE
mozilla_nimbus_schemas-3001.0.0.dist-info/METADATA
mozilla_nimbus_schemas-3001.0.0.dist-info/WHEEL
mozilla_nimbus_schemas-3001.0.0.dist-info/RECORD
