Metadata-Version: 2.1
Name: mozilla-nimbus-schemas
Version: 3001.0.0
Summary: Schemas used by Mozilla Nimbus and related projects.
License: MPL 2.0
Author: mikewilli
Requires-Python: >=3.10,<4.0
Classifier: License :: Other/Proprietary License
Classifier: Programming Language :: Python :: 3
Classifier: Programming Language :: Python :: 3.10
Classifier: Programming Language :: Python :: 3.11
Classifier: Programming Language :: Python :: 3.12
Classifier: Programming Language :: Python :: 3.13
Requires-Dist: jsonschema (>=4.23.0,<5.0.0)
Requires-Dist: polyfactory (>=2.7.2,<3.0.0)
Requires-Dist: pydantic (>=2,<3)
Requires-Dist: typing-extensions (>=4.0.1)
